MANIFEST.in
README.rst
setup.cfg
setup.py
collective/__init__.py
collective.qabank.egg-info/PKG-INFO
collective.qabank.egg-info/SOURCES.txt
collective.qabank.egg-info/dependency_links.txt
collective.qabank.egg-info/entry_points.txt
collective.qabank.egg-info/namespace_packages.txt
collective.qabank.egg-info/not-zip-safe
collective.qabank.egg-info/paster_plugins.txt
collective.qabank.egg-info/requires.txt
collective.qabank.egg-info/top_level.txt
collective/qabank/__init__.py
collective/qabank/configure.zcml
collective/qabank/interfaces.py
collective/qabank/setuphandlers.py
collective/qabank/behavior/README.txt
collective/qabank/behavior/__init__.py
collective/qabank/behavior/configure.zcml
collective/qabank/browser/README.txt
collective/qabank/browser/__init__.py
collective/qabank/browser/answer_view.py
collective/qabank/browser/qa_bank_view.py
collective/qabank/browser/question_view.py
collective/qabank/browser/templates/answer_view.pt
collective/qabank/browser/templates/qa_bank_view.pt
collective/qabank/browser/templates/question_view.pt
collective/qabank/content/README.txt
collective/qabank/content/__init__.py
collective/qabank/content/answer.py
collective/qabank/content/qa_bank.py
collective/qabank/content/question.py
collective/qabank/locales/README.txt
collective/qabank/portlet/__init__.py
collective/qabank/portlet/configure.zcml
collective/qabank/profiles/default/browserlayer.xml
collective/qabank/profiles/default/collective.qabank.marker.txt
collective/qabank/profiles/default/cssregistry.xml
collective/qabank/profiles/default/jsregistry.xml
collective/qabank/profiles/default/metadata.xml
collective/qabank/profiles/default/portlets.xml
collective/qabank/profiles/default/types.xml
collective/qabank/profiles/default/types/collective.qabank.answer.xml
collective/qabank/profiles/default/types/collective.qabank.qabank.xml
collective/qabank/profiles/default/types/collective.qabank.question.xml
collective/qabank/schemaextender/__init__.py
collective/qabank/static/README.txt
collective/qabank/upgrades/__init__.py
collective/qabank/upgrades/handlers.py
collective/qabank/upgrades/profiles.py
collective/qabank/viewlet/__init__.py
collective/qabank/vocabulary/__init__.py
docs/HISTORY.rst
docs/INSTALL.rst
docs/LICENSE.GPL
docs/LICENSE.txt